datapizza/embedders/openai/__init__.py
datapizza/embedders/openai/openai.py
datapizza_ai_embedders_openai-0.0.5.dist-info/METADATA
datapizza_ai_embedders_openai-0.0.5.dist-info/WHEEL
datapizza_ai_embedders_openai-0.0.5.dist-info/RECORD
